rtems_proxy/__init__.py
rtems_proxy/__main__.py
rtems_proxy/_version.py
rtems_proxy/configure.py
rtems_proxy/connect.py
rtems_proxy/copy.py
rtems_proxy/globals.py
rtems_proxy/rsync.sh.jinja
rtems_proxy/telnet.py
rtems_proxy/trace.py
rtems_proxy/utils.py
rtems_proxy-2.1.0.dist-info/licenses/LICENSE
rtems_proxy-2.1.0.dist-info/METADATA
rtems_proxy-2.1.0.dist-info/WHEEL
rtems_proxy-2.1.0.dist-info/entry_points.txt
rtems_proxy-2.1.0.dist-info/top_level.txt
rtems_proxy-2.1.0.dist-info/RECORD
