Metadata-Version: 2.4
Name: rtems-proxy
Version: 2.1.0
Summary: Support for a K8S proxy container in controlling and monitoring RTEMS EPICS IOCs
Author-email: Giles Knap <giles.knap@diamond.ac.uk>
License:                                  Apache License
Project-URL: GitHub, https://github.com/epics-containers/rtems-proxy
Classifier: Development Status :: 3 - Alpha
Classifier: License :: OSI Approved :: Apache Software License
Classifier: Programming Language :: Python :: 3.11
Classifier: Programming Language :: Python :: 3.12
Classifier: Programming Language :: Python :: 3.13
Requires-Python: >=3.11
License-File: LICENSE
Requires-Dist: jinja2
Requires-Dist: pexpect
Requires-Dist: ruamel.yaml
Requires-Dist: stdio-socket>=1.3.1
Requires-Dist: telnetlib3
Requires-Dist: typer
Dynamic: license-file
